cpu_top/Global_defines.vh

`define  ADDR_WIDTH 8;
`define DATA_WIDTH 32;

cpu_top/Mem_top.v
// this file is the simple register file that is used as a simple soc simuilation 

//`include "Global_defines.vh"

 module Mem_top #(parameter MEM_DEPTH=8 ,parameter DATA_WIDTH=32 ) 
                ( input[ADDR_WIDTH-1:0] addr ,
                 input req_valid ,input WE,
                 input clk ,reset ,
                 inout[DATA_WIDTH-1:0]  Data,
                 output data_valid ) ; // think of it as a successful read/write status bit  

      localparam ADDR_WIDTH=$clog2(MEM_DEPTH);
       integer i ;
       reg[DATA_WIDTH-1:0] data_reg;
       reg data_valid_reg;
             // 1Read /1 Write Memory model 

		 //Main Memory
		 reg[DATA_WIDTH-1:0] Mem[0:MEM_DEPTH-1];

		 always@(posedge clk or posedge reset)
		 begin
			if(reset)
			begin 
                          
			   for(i=0;i<MEM_DEPTH;i=i+1) begin 
				   Mem[i]=i;  // just for creating a test case 
			   end 

			   data_valid_reg=1'b0;

		   end 


		   // Read 
		   if(req_valid && !WE)
		   begin 
		   data_reg = Mem[addr];
		   data_valid_reg=1'b1;
	           end 
                   //write 
		   if(req_valid && WE )
		   begin 
		   Mem[addr]=Data;
		   data_valid_reg=1'b1;
	           end 

		//   data_valid_reg=1'b0;

	   end  //always block 
	    
	    assign Data=data_reg;
	    assign data_valid=data_valid_reg;

	    //there are some loopholes in data_valid logic , need to fix it
	    //chnage#2 



  endmodule

cpu_top/cpu_core.v

// Development of a basic risc -v cpu core .
// 26h july 
//`include "Global_defines.vh"

`define RESET 2'b00
`define TX 2'b01 
`define WAIT 2'b11
`define RX 12'b10


 module cpu_top #(parameter MEM_DEPTH=8 ,parameter DATA_WIDTH=32 ) 
   (
	output[ADDR_WIDTH -1:0] Addr ,
	inout[DATA_WIDTH-1:0] Data,
	output we,
        output  req_valid,
//	input intr,  to be implemented later 
	input clk ,
	input reset,
	input data_valid

        );
localparam STATE_WIDTH=2;
 localparam ADDR_WIDTH=$clog2(MEM_DEPTH);
     // top level 

     //architectural registers for simple registers  

   //  reg[31:0] A, B,C,D,E  //specify the registers later 
     reg req_valid_reg,we_reg;
     reg [ADDR_WIDTH -1:0] Addr_reg; 
     reg[STATE_WIDTH-1:0] PresentState , NextState;
     //program counter
     reg[31:0] ProgramCounter;
     reg PC_v; // program counter valid 
     // instruction register 
     reg[31:0] InstructionRegister;
     reg IR_v; //Instruction regsiter valid 

     always@(posedge clk or posedge reset)
     begin
	    		      
           // increment program counter 
	   // There will be some Arbitration scheme required in future 
	   // to arbitrate between requests from Instruction and data sides
	   // change (1) 
	  if(reset)
	  begin 
	  NextState=`RESET;
	  end 
	  
           
	    case(PresentState) 

	    
		    
		    `RESET :    begin
				ProgramCounter=0;  // Initial value of Program counter , can be programmed to other values .
             			InstructionRegister=0;
                        PC_v=1'b1; IR_v=1'b0;
                     if(reset)
                     begin 
                     NextState=`RESET;
                     end    
                     
                                 
				 we_reg=1'b0;
				 if(PC_v)
				 begin 
				  NextState=`TX;
       				 end 
       				 end

               `TX:   begin 
		            Addr_reg=ProgramCounter;
			    req_valid_reg=1'b1;
			    PC_v=1'b0; IR_v=1'b0;
			    NextState =`WAIT;
			    we_reg=1'b0;
 			    end 
		     `WAIT :  begin
			      req_valid_reg=1'b1; 
			      if(data_valid)
			      begin 
			      NextState=`RX;

		 	      end 
		 	      end

		    `RX : begin 
		          InstructionRegister=Data;
			  IR_v=1'b1;
			  if(ProgramCounter==MEM_DEPTH)
			  begin ProgramCounter=0;
			  end
			  ProgramCounter=ProgramCounter+1; 
			  PC_v=1'b1;
			  req_valid_reg=1'b0;
			  // in future we need to implement a buffer ,we need
			  // to sample a busy signal from the instruction
			  // buffer and gate this transition 
			  NextState=`TX;
		          end

                endcase 

		PresentState=NextState;

      end 		

   assign Addr=Addr_reg;
   assign req_valid=req_valid_reg;
   assign we =we_reg ;



endmodule

cpu_top/Soc.v
// This is the soc top integrating the cpu core and Mem_top via a custom
// defined bus and bus protocol 

//`include "Global_defines.vh"

`include "cpu_core.v"
`include "Mem_top.v"

module SOC #(parameter MEM_DEPTH=8 ,parameter DATA_WIDTH=32)
   (
	input clk ,
	input reset

	// to be added ports for debug 
	);

	//wire [DATA_WIDTH-1:0] data;
	localparam ADDR_WIDTH =$clog2(MEM_DEPTH);
	wire [ADDR_WIDTH-1:0] addr;wire[DATA_WIDTH-1:0] data;
	wire req_valid,valid_data ,we;

     cpu_top #(MEM_DEPTH,DATA_WIDTH)	core1(.clk(clk),
	          .reset(reset),
		  .Addr(addr),
		  .Data(data),
		  .req_valid(req_valid),
		  .data_valid(valid_data),
		  .we(we)
	  );


	  Mem_top #(MEM_DEPTH,DATA_WIDTH) Mem(.clk(clk),
	          .reset(reset),
		  .addr(addr),
		  .Data(data),
		  .req_valid(req_valid),
		  .data_valid(valid_data),
		  .WE(we)
	  );


	  endmodule

cpu_top/rtl/soc_tb.sv
`timescale 1ns / 1ps
//////////////////////////////////////////////////////////////////////////////////
// Company: 
// Engineer: 
// 
// Create Date: 07/26/2024 02:23:17 PM
// Design Name: 
// Module Name: soc_tb
// Project Name: 
// Target Devices: 
// Tool Versions: 
// Description: 
// 
// Dependencies: 
// 
// Revision:
// Revision 0.01 - File Created
// Additional Comments:
// 
//////////////////////////////////////////////////////////////////////////////////




module SOC_tb;

    // Parameters for width
   parameter DATA_WIDTH = 32;
   parameter MEM_DEPTH = 64;

    // Testbench signals
    reg clk;
    reg reset;
     localparam ADDR_WIDTH=$clog2(MEM_DEPTH);
    // Wires to connect to the SOC module
    wire [ADDR_WIDTH-1:0] addr;
    wire req_valid, valid_data, we;
    wire [DATA_WIDTH-1:0] data;

    // Instantiate the SOC module
    SOC #(MEM_DEPTH,DATA_WIDTH)
    dut (
        .clk(clk),
        .reset(reset)
        // Add debug ports if necessary
    );

    // Clock generation
    always #10 clk = ~clk;

    initial begin
        // Initialize signals
        clk = 0;
        reset = 1;

        // Apply reset
        #50;
        reset = 0;

        // Stimulus to the SOC module
        // Add stimulus code here, e.g., setting req_valid, we, addr, and data

        // Wait for a while
        #100;

	#10000;
	$finish; 
        // End the simulation
      //  $finish;
    end

    initial begin
        // Monitoring signals
        $monitor("At time %t, clk = %b, reset = %b, addr = %h, req_valid = %b, valid_data = %b, we = %b, data = %h",
                 $time, clk, reset, addr, req_valid, valid_data, we, data);
    end

 initial begin
        // Dump waveforms
        $dumpfile("waves.vcd");
        $dumpvars(0, SOC_tb);       // Include top-level signals in the testbench module
        $dumpvars(1, SOC_tb.dut);   // Include signals in the counter module (uut instance)
	// $dumpvars(1, testbench.dut); 
    end


endmodule

cpu_top/waves.vcd
$date
	Fri Jul 26 20:21:10 2024
$end
$version
	Icarus Verilog
$end
$timescale
	1ps
$end
$scope module SOC_tb $end
$var wire 4 ! addr [3:0] $end
$var wire 32 " data [31:0] $end
$var wire 1 # req_valid $end
$var wire 1 $ valid_data $end
$var wire 1 % we $end
$var reg 1 & clk $end
$var reg 1 ' reset $end
$scope module dut $end
$var wire 1 & clk $end
$var wire 1 ' reset $end
$var wire 1 ( we $end
$var wire 1 ) valid_data $end
$var wire 1 * req_valid $end
$var wire 32 + data [31:0] $end
$var wire 4 , addr [3:0] $end
$scope module Mem $end
$var wire 32 - Data [31:0] $end
$var wire 1 & clk $end
$var wire 1 ) data_valid $end
$var wire 1 ' reset $end
$var wire 1 * req_valid $end
$var wire 4 . addr [3:0] $end
$var wire 1 ( WE $end
$var reg 32 / data_reg [31:0] $end
$var reg 1 0 data_valid_reg $end
$var integer 32 1 i [31:0] $end
$upscope $end
$scope module core1 $end
$var wire 4 2 Addr [3:0] $end
$var wire 32 3 Data [31:0] $end
$var wire 1 & clk $end
$var wire 1 ) data_valid $end
$var wire 1 * req_valid $end
$var wire 1 ' reset $end
$var wire 1 ( we $end
$var reg 4 4 Addr_reg [3:0] $end
$var reg 1 5 IR_v $end
$var reg 32 6 InstructionRegister [31:0] $end
$var reg 2 7 NextState [1:0] $end
$var reg 1 8 PC_v $end
$var reg 2 9 PresentState [1:0] $end
$var reg 32 : ProgramCounter [31:0] $end
$var reg 1 ; req_valid_reg $end
$var reg 1 < we_reg $end
$upscope $end
$upscope $end
$upscope $end
$scope module SOC_tb $end
$scope module dut $end
$upscope $end
$upscope $end
$enddefinitions $end
#0
$dumpvars
x<
x;
bx :
b0 9
x8
b0 7
bx 6
x5
bx 4
bx 3
bx 2
b10000 1
00
bx /
bx .
bx -
bx ,
bx +
x*
0)
x(
1'
0&
z%
z$
z#
bz "
bz !
$end
#10000
b10000 1
b1 9
b1 7
0(
0<
05
18
b0 6
b0 :
1&
#20000
0&
#30000
b11 9
08
1*
1;
b0 ,
b0 .
b0 2
b0 4
b11 7
b10000 1
1&
#40000
0&
#50000
1)
10
b0 +
b0 -
b0 3
b0 /
1&
0'
#60000
0&
#70000
b10 9
b10 7
1&
#80000
0&
#90000
b1 9
b1 7
0*
0;
18
b1 :
15
1&
#100000
0&
#110000
b11 9
b11 7
05
08
1*
1;
b1 ,
b1 .
b1 2
b1 4
1&
#120000
0&
#130000
b1 +
b1 -
b1 3
b1 /
b10 9
b10 7
1&
#140000
0&
#150000
b1 9
b1 7
0*
0;
18
b10 :
15
b1 6
1&
#160000
0&
#170000
b10 +
b10 -
b10 3
b10 /
b11 9
b11 7
05
08
1*
1;
b10 ,
b10 .
b10 2
b10 4
1&
#180000
0&
#190000
b10 9
b10 7
1&
#200000
0&
#210000
b1 9
b1 7
0*
0;
18
b11 :
15
b10 6
1&
#220000
0&
#230000
b11 9
b11 7
05
08
1*
1;
b11 ,
b11 .
b11 2
b11 4
1&
#240000
0&
#250000
b11 +
b11 -
b11 3
b11 /
b10 9
b10 7
1&
#260000
0&
#270000
b1 9
b1 7
0*
0;
18
b100 :
15
b11 6
1&
#280000
0&
#290000
b100 +
b100 -
b100 3
b100 /
b11 9
b11 7
05
08
1*
1;
b100 ,
b100 .
b100 2
b100 4
1&
#300000
0&
#310000
b10 9
b10 7
1&
#320000
0&
#330000
b1 9
b1 7
0*
0;
18
b101 :
15
b100 6
1&
#340000
0&
#350000
b11 9
b11 7
05
08
1*
1;
b101 ,
b101 .
b101 2
b101 4
1&
#360000
0&
#370000
b101 +
b101 -
b101 3
b101 /
b10 9
b10 7
1&
#380000
0&
#390000
b1 9
b1 7
0*
0;
18
b110 :
15
b101 6
1&
#400000
0&
#410000
b110 +
b110 -
b110 3
b110 /
b11 9
b11 7
05
08
1*
1;
b110 ,
b110 .
b110 2
b110 4
1&
#420000
0&
#430000
b10 9
b10 7
1&
#440000
0&
#450000
b1 9
b1 7
0*
0;
18
b111 :
15
b110 6
1&
#460000
0&
#470000
b11 9
b11 7
05
08
1*
1;
b111 ,
b111 .
b111 2
b111 4
1&
#480000
0&
#490000
b111 +
b111 -
b111 3
b111 /
b10 9
b10 7
1&
#500000
0&
#510000
b1 9
b1 7
0*
0;
18
b1000 :
15
b111 6
1&
#520000
0&
#530000
b1000 +
b1000 -
b1000 3
b1000 /
b11 9
b11 7
05
08
1*
1;
b1000 ,
b1000 .
b1000 2
b1000 4
1&
#540000
0&
#550000
b10 9
b10 7
1&
#560000
0&
#570000
b1 9
b1 7
0*
0;
18
b1001 :
15
b1000 6
1&
#580000
0&
#590000
b11 9
b11 7
05
08
1*
1;
b1001 ,
b1001 .
b1001 2
b1001 4
1&
#600000
0&
#610000
b1001 +
b1001 -
b1001 3
b1001 /
b10 9
b10 7
1&
#620000
0&
#630000
b1 9
b1 7
0*
0;
18
b1010 :
15
b1001 6
1&
#640000
0&
#650000
b1010 +
b1010 -
b1010 3
b1010 /
b11 9
b11 7
05
08
1*
1;
b1010 ,
b1010 .
b1010 2
b1010 4
1&
#660000
0&
#670000
b10 9
b10 7
1&
#680000
0&
#690000
b1 9
b1 7
0*
0;
18
b1011 :
15
b1010 6
1&
#700000
0&
#710000
b11 9
b11 7
05
08
1*
1;
b1011 ,
b1011 .
b1011 2
b1011 4
1&
#720000
0&
#730000
b1011 +
b1011 -
b1011 3
b1011 /
b10 9
b10 7
1&
#740000
0&
#750000
b1 9
b1 7
0*
0;
18
b1100 :
15
b1011 6
1&
#760000
0&
#770000
b1100 +
b1100 -
b1100 3
b1100 /
b11 9
b11 7
05
08
1*
1;
b1100 ,
b1100 .
b1100 2
b1100 4
1&
#780000
0&
#790000
b10 9
b10 7
1&
#800000
0&
#810000
b1 9
b1 7
0*
0;
18
b1101 :
15
b1100 6
1&
#820000
0&
#830000
b11 9
b11 7
05
08
1*
1;
b1101 ,
b1101 .
b1101 2
b1101 4
1&
#840000
0&
#850000
b1101 +
b1101 -
b1101 3
b1101 /
b10 9
b10 7
1&
#860000
0&
#870000
b1 9
b1 7
0*
0;
18
b1110 :
15
b1101 6
1&
#880000
0&
#890000
b1110 +
b1110 -
b1110 3
b1110 /
b11 9
b11 7
05
08
1*
1;
b1110 ,
b1110 .
b1110 2
b1110 4
1&
#900000
0&
#910000
b10 9
b10 7
1&
#920000
0&
#930000
b1 9
b1 7
0*
0;
18
b1111 :
15
b1110 6
1&
#940000
0&
#950000
b11 9
b11 7
05
08
1*
1;
b1111 ,
b1111 .
b1111 2
b1111 4
1&
#960000
0&
#970000
b1111 +
b1111 -
b1111 3
b1111 /
b10 9
b10 7
1&
#980000
0&
#990000
b1 9
b1 7
0*
0;
18
b10000 :
15
b1111 6
1&
#1000000
0&
#1010000
b0 +
b0 -
b0 3
b0 /
b11 9
b11 7
05
08
1*
1;
b0 ,
b0 .
b0 2
b0 4
1&
#1020000
0&
#1030000
b10 9
b10 7
1&
#1040000
0&
#1050000
b1 9
b1 7
0*
0;
18
b1 :
15
b0 6
1&
#1060000
0&
#1070000
b11 9
b11 7
05
08
1*
1;
b1 ,
b1 .
b1 2
b1 4
1&
#1080000
0&
#1090000
b1 +
b1 -
b1 3
b1 /
b10 9
b10 7
1&
#1100000
0&
#1110000
b1 9
b1 7
0*
0;
18
b10 :
15
b1 6
1&
#1120000
0&
#1130000
b10 +
b10 -
b10 3
b10 /
b11 9
b11 7
05
08
1*
1;
b10 ,
b10 .
b10 2
b10 4
1&
#1140000
0&
#1150000
b10 9
b10 7
1&
#1160000
0&
#1170000
b1 9
b1 7
0*
0;
18
b11 :
15
b10 6
1&
#1180000
0&
#1190000
b11 9
b11 7
05
08
1*
1;
b11 ,
b11 .
b11 2
b11 4
1&
#1200000
0&
#1210000
b11 +
b11 -
b11 3
b11 /
b10 9
b10 7
1&
#1220000
0&
#1230000
b1 9
b1 7
0*
0;
18
b100 :
15
b11 6
1&
#1240000
0&
#1250000
b100 +
b100 -
b100 3
b100 /
b11 9
b11 7
05
08
1*
1;
b100 ,
b100 .
b100 2
b100 4
1&
#1260000
0&
#1270000
b10 9
b10 7
1&
#1280000
0&
#1290000
b1 9
b1 7
0*
0;
18
b101 :
15
b100 6
1&
#1300000
0&
#1310000
b11 9
b11 7
05
08
1*
1;
b101 ,
b101 .
b101 2
b101 4
1&
#1320000
0&
#1330000
b101 +
b101 -
b101 3
b101 /
b10 9
b10 7
1&
#1340000
0&
#1350000
b1 9
b1 7
0*
0;
18
b110 :
15
b101 6
1&
#1360000
0&
#1370000
b110 +
b110 -
b110 3
b110 /
b11 9
b11 7
05
08
1*
1;
b110 ,
b110 .
b110 2
b110 4
1&
#1380000
0&
#1390000
b10 9
b10 7
1&
#1400000
0&
#1410000
b1 9
b1 7
0*
0;
18
b111 :
15
b110 6
1&
#1420000
0&
#1430000
b11 9
b11 7
05
08
1*
1;
b111 ,
b111 .
b111 2
b111 4
1&
#1440000
0&
#1450000
b111 +
b111 -
b111 3
b111 /
b10 9
b10 7
1&
#1460000
0&
#1470000
b1 9
b1 7
0*
0;
18
b1000 :
15
b111 6
1&
#1480000
0&
#1490000
b1000 +
b1000 -
b1000 3
b1000 /
b11 9
b11 7
05
08
1*
1;
b1000 ,
b1000 .
b1000 2
b1000 4
1&
#1500000
0&
#1510000
b10 9
b10 7
1&
#1520000
0&
#1530000
b1 9
b1 7
0*
0;
18
b1001 :
15
b1000 6
1&
#1540000
0&
#1550000
b11 9
b11 7
05
08
1*
1;
b1001 ,
b1001 .
b1001 2
b1001 4
1&
#1560000
0&
#1570000
b1001 +
b1001 -
b1001 3
b1001 /
b10 9
b10 7
1&
#1580000
0&
#1590000
b1 9
b1 7
0*
0;
18
b1010 :
15
b1001 6
1&
#1600000
0&
#1610000
b1010 +
b1010 -
b1010 3
b1010 /
b11 9
b11 7
05
08
1*
1;
b1010 ,
b1010 .
b1010 2
b1010 4
1&
#1620000
0&
#1630000
b10 9
b10 7
1&
#1640000
0&
#1650000
b1 9
b1 7
0*
0;
18
b1011 :
15
b1010 6
1&
#1660000
0&
#1670000
b11 9
b11 7
05
08
1*
1;
b1011 ,
b1011 .
b1011 2
b1011 4
1&
#1680000
0&
#1690000
b1011 +
b1011 -
b1011 3
b1011 /
b10 9
b10 7
1&
#1700000
0&
#1710000
b1 9
b1 7
0*
0;
18
b1100 :
15
b1011 6
1&
#1720000
0&
#1730000
b1100 +
b1100 -
b1100 3
b1100 /
b11 9
b11 7
05
08
1*
1;
b1100 ,
b1100 .
b1100 2
b1100 4
1&
#1740000
0&
#1750000
b10 9
b10 7
1&
#1760000
0&
#1770000
b1 9
b1 7
0*
0;
18
b1101 :
15
b1100 6
1&
#1780000
0&
#1790000
b11 9
b11 7
05
08
1*
1;
b1101 ,
b1101 .
b1101 2
b1101 4
1&
#1800000
0&
#1810000
b1101 +
b1101 -
b1101 3
b1101 /
b10 9
b10 7
1&
#1820000
0&
#1830000
b1 9
b1 7
0*
0;
18
b1110 :
15
b1101 6
1&
#1840000
0&
#1850000
b1110 +
b1110 -
b1110 3
b1110 /
b11 9
b11 7
05
08
1*
1;
b1110 ,
b1110 .
b1110 2
b1110 4
1&
#1860000
0&
#1870000
b10 9
b10 7
1&
#1880000
0&
#1890000
b1 9
b1 7
0*
0;
18
b1111 :
15
b1110 6
1&
#1900000
0&
#1910000
b11 9
b11 7
05
08
1*
1;
b1111 ,
b1111 .
b1111 2
b1111 4
1&
#1920000
0&
#1930000
b1111 +
b1111 -
b1111 3
b1111 /
b10 9
b10 7
1&
#1940000
0&
#1950000
b1 9
b1 7
0*
0;
18
b10000 :
15
b1111 6
1&
#1960000
0&
#1970000
b0 +
b0 -
b0 3
b0 /
b11 9
b11 7
05
08
1*
1;
b0 ,
b0 .
b0 2
b0 4
1&
#1980000
0&
#1990000
b10 9
b10 7
1&
#2000000
0&
#2010000
b1 9
b1 7
0*
0;
18
b1 :
15
b0 6
1&
#2020000
0&
#2030000
b11 9
b11 7
05
08
1*
1;
b1 ,
b1 .
b1 2
b1 4
1&
#2040000
0&
#2050000
b1 +
b1 -
b1 3
b1 /
b10 9
b10 7
1&
#2060000
0&
#2070000
b1 9
b1 7
0*
0;
18
b10 :
15
b1 6
1&
#2080000
0&
#2090000
b10 +
b10 -
b10 3
b10 /
b11 9
b11 7
05
08
1*
1;
b10 ,
b10 .
b10 2
b10 4
1&
#2100000
0&
#2110000
b10 9
b10 7
1&
#2120000
0&
#2130000
b1 9
b1 7
0*
0;
18
b11 :
15
b10 6
1&
#2140000
0&
#2150000
b11 9
b11 7
05
08
1*
1;
b11 ,
b11 .
b11 2
b11 4
1&
#2160000
0&
#2170000
b11 +
b11 -
b11 3
b11 /
b10 9
b10 7
1&
#2180000
0&
#2190000
b1 9
b1 7
0*
0;
18
b100 :
15
b11 6
1&
#2200000
0&
#2210000
b100 +
b100 -
b100 3
b100 /
b11 9
b11 7
05
08
1*
1;
b100 ,
b100 .
b100 2
b100 4
1&
#2220000
0&
#2230000
b10 9
b10 7
1&
#2240000
0&
#2250000
b1 9
b1 7
0*
0;
18
b101 :
15
b100 6
1&
#2260000
0&
#2270000
b11 9
b11 7
05
08
1*
1;
b101 ,
b101 .
b101 2
b101 4
1&
#2280000
0&
#2290000
b101 +
b101 -
b101 3
b101 /
b10 9
b10 7
1&
#2300000
0&
#2310000
b1 9
b1 7
0*
0;
18
b110 :
15
b101 6
1&
#2320000
0&
#2330000
b110 +
b110 -
b110 3
b110 /
b11 9
b11 7
05
08
1*
1;
b110 ,
b110 .
b110 2
b110 4
1&
#2340000
0&
#2350000
b10 9
b10 7
1&
#2360000
0&
#2370000
b1 9
b1 7
0*
0;
18
b111 :
15
b110 6
1&
#2380000
0&
#2390000
b11 9
b11 7
05
08
1*
1;
b111 ,
b111 .
b111 2
b111 4
1&
#2400000
0&
#2410000
b111 +
b111 -
b111 3
b111 /
b10 9
b10 7
1&
#2420000
0&
#2430000
b1 9
b1 7
0*
0;
18
b1000 :
15
b111 6
1&
#2440000
0&
#2450000
b1000 +
b1000 -
b1000 3
b1000 /
b11 9
b11 7
05
08
1*
1;
b1000 ,
b1000 .
b1000 2
b1000 4
1&
#2460000
0&
#2470000
b10 9
b10 7
1&
#2480000
0&
#2490000
b1 9
b1 7
0*
0;
18
b1001 :
15
b1000 6
1&
#2500000
0&
#2510000
b11 9
b11 7
05
08
1*
1;
b1001 ,
b1001 .
b1001 2
b1001 4
1&
#2520000
0&
#2530000
b1001 +
b1001 -
b1001 3
b1001 /
b10 9
b10 7
1&
#2540000
0&
#2550000
b1 9
b1 7
0*
0;
18
b1010 :
15
b1001 6
1&
#2560000
0&
#2570000
b1010 +
b1010 -
b1010 3
b1010 /
b11 9
b11 7
05
08
1*
1;
b1010 ,
b1010 .
b1010 2
b1010 4
1&
#2580000
0&
#2590000
b10 9
b10 7
1&
#2600000
0&
#2610000
b1 9
b1 7
0*
0;
18
b1011 :
15
b1010 6
1&
#2620000
0&
#2630000
b11 9
b11 7
05
08
1*
1;
b1011 ,
b1011 .
b1011 2
b1011 4
1&
#2640000
0&
#2650000
b1011 +
b1011 -
b1011 3
b1011 /
b10 9
b10 7
1&
#2660000
0&
#2670000
b1 9
b1 7
0*
0;
18
b1100 :
15
b1011 6
1&
#2680000
0&
#2690000
b1100 +
b1100 -
b1100 3
b1100 /
b11 9
b11 7
05
08
1*
1;
b1100 ,
b1100 .
b1100 2
b1100 4
1&
#2700000
0&
#2710000
b10 9
b10 7
1&
#2720000
0&
#2730000
b1 9
b1 7
0*
0;
18
b1101 :
15
b1100 6
1&
#2740000
0&
#2750000
b11 9
b11 7
05
08
1*
1;
b1101 ,
b1101 .
b1101 2
b1101 4
1&
#2760000
0&
#2770000
b1101 +
b1101 -
b1101 3
b1101 /
b10 9
b10 7
1&
#2780000
0&
#2790000
b1 9
b1 7
0*
0;
18
b1110 :
15
b1101 6
1&
#2800000
0&
#2810000
b1110 +
b1110 -
b1110 3
b1110 /
b11 9
b11 7
05
08
1*
1;
b1110 ,
b1110 .
b1110 2
b1110 4
1&
#2820000
0&
#2830000
b10 9
b10 7
1&
#2840000
0&
#2850000
b1 9
b1 7
0*
0;
18
b1111 :
15
b1110 6
1&
#2860000
0&
#2870000
b11 9
b11 7
05
08
1*
1;
b1111 ,
b1111 .
b1111 2
b1111 4
1&
#2880000
0&
#2890000
b1111 +
b1111 -
b1111 3
b1111 /
b10 9
b10 7
1&
#2900000
0&
#2910000
b1 9
b1 7
0*
0;
18
b10000 :
15
b1111 6
1&
#2920000
0&
#2930000
b0 +
b0 -
b0 3
b0 /
b11 9
b11 7
05
08
1*
1;
b0 ,
b0 .
b0 2
b0 4
1&
#2940000
0&
#2950000
b10 9
b10 7
1&
#2960000
0&
#2970000
b1 9
b1 7
0*
0;
18
b1 :
15
b0 6
1&
#2980000
0&
#2990000
b11 9
b11 7
05
08
1*
1;
b1 ,
b1 .
b1 2
b1 4
1&
#3000000
0&
#3010000
b1 +
b1 -
b1 3
b1 /
b10 9
b10 7
1&
#3020000
0&
#3030000
b1 9
b1 7
0*
0;
18
b10 :
15
b1 6
1&
#3040000
0&
#3050000
b10 +
b10 -
b10 3
b10 /
b11 9
b11 7
05
08
1*
1;
b10 ,
b10 .
b10 2
b10 4
1&
#3060000
0&
#3070000
b10 9
b10 7
1&
#3080000
0&
#3090000
b1 9
b1 7
0*
0;
18
b11 :
15
b10 6
1&
#3100000
0&
#3110000
b11 9
b11 7
05
08
1*
1;
b11 ,
b11 .
b11 2
b11 4
1&
#3120000
0&
#3130000
b11 +
b11 -
b11 3
b11 /
b10 9
b10 7
1&
#3140000
0&
#3150000
b1 9
b1 7
0*
0;
18
b100 :
15
b11 6
1&
#3160000
0&
#3170000
b100 +
b100 -
b100 3
b100 /
b11 9
b11 7
05
08
1*
1;
b100 ,
b100 .
b100 2
b100 4
1&
#3180000
0&
#3190000
b10 9
b10 7
1&
#3200000
0&
#3210000
b1 9
b1 7
0*
0;
18
b101 :
15
b100 6
1&
#3220000
0&
#3230000
b11 9
b11 7
05
08
1*
1;
b101 ,
b101 .
b101 2
b101 4
1&
#3240000
0&
#3250000
b101 +
b101 -
b101 3
b101 /
b10 9
b10 7
1&
#3260000
0&
#3270000
b1 9
b1 7
0*
0;
18
b110 :
15
b101 6
1&
#3280000
0&
#3290000
b110 +
b110 -
b110 3
b110 /
b11 9
b11 7
05
08
1*
1;
b110 ,
b110 .
b110 2
b110 4
1&
#3300000
0&
#3310000
b10 9
b10 7
1&
#3320000
0&
#3330000
b1 9
b1 7
0*
0;
18
b111 :
15
b110 6
1&
#3340000
0&
#3350000
b11 9
b11 7
05
08
1*
1;
b111 ,
b111 .
b111 2
b111 4
1&
#3360000
0&
#3370000
b111 +
b111 -
b111 3
b111 /
b10 9
b10 7
1&
#3380000
0&
#3390000
b1 9
b1 7
0*
0;
18
b1000 :
15
b111 6
1&
#3400000
0&
#3410000
b1000 +
b1000 -
b1000 3
b1000 /
b11 9
b11 7
05
08
1*
1;
b1000 ,
b1000 .
b1000 2
b1000 4
1&
#3420000
0&
#3430000
b10 9
b10 7
1&
#3440000
0&
#3450000
b1 9
b1 7
0*
0;
18
b1001 :
15
b1000 6
1&
#3460000
0&
#3470000
b11 9
b11 7
05
08
1*
1;
b1001 ,
b1001 .
b1001 2
b1001 4
1&
#3480000
0&
#3490000
b1001 +
b1001 -
b1001 3
b1001 /
b10 9
b10 7
1&
#3500000
0&
#3510000
b1 9
b1 7
0*
0;
18
b1010 :
15
b1001 6
1&
#3520000
0&
#3530000
b1010 +
b1010 -
b1010 3
b1010 /
b11 9
b11 7
05
08
1*
1;
b1010 ,
b1010 .
b1010 2
b1010 4
1&
#3540000
0&
#3550000
b10 9
b10 7
1&
#3560000
0&
#3570000
b1 9
b1 7
0*
0;
18
b1011 :
15
b1010 6
1&
#3580000
0&
#3590000
b11 9
b11 7
05
08
1*
1;
b1011 ,
b1011 .
b1011 2
b1011 4
1&
#3600000
0&
#3610000
b1011 +
b1011 -
b1011 3
b1011 /
b10 9
b10 7
1&
#3620000
0&
#3630000
b1 9
b1 7
0*
0;
18
b1100 :
15
b1011 6
1&
#3640000
0&
#3650000
b1100 +
b1100 -
b1100 3
b1100 /
b11 9
b11 7
05
08
1*
1;
b1100 ,
b1100 .
b1100 2
b1100 4
1&
#3660000
0&
#3670000
b10 9
b10 7
1&
#3680000
0&
#3690000
b1 9
b1 7
0*
0;
18
b1101 :
15
b1100 6
1&
#3700000
0&
#3710000
b11 9
b11 7
05
08
1*
1;
b1101 ,
b1101 .
b1101 2
b1101 4
1&
#3720000
0&
#3730000
b1101 +
b1101 -
b1101 3
b1101 /
b10 9
b10 7
1&
#3740000
0&
#3750000
b1 9
b1 7
0*
0;
18
b1110 :
15
b1101 6
1&
#3760000
0&
#3770000
b1110 +
b1110 -
b1110 3
b1110 /
b11 9
b11 7
05
08
1*
1;
b1110 ,
b1110 .
b1110 2
b1110 4
1&
#3780000
0&
#3790000
b10 9
b10 7
1&
#3800000
0&
#3810000
b1 9
b1 7
0*
0;
18
b1111 :
15
b1110 6
1&
#3820000
0&
#3830000
b11 9
b11 7
05
08
1*
1;
b1111 ,
b1111 .
b1111 2
b1111 4
1&
#3840000
0&
#3850000
b1111 +
b1111 -
b1111 3
b1111 /
b10 9
b10 7
1&
#3860000
0&
#3870000
b1 9
b1 7
0*
0;
18
b10000 :
15
b1111 6
1&
#3880000
0&
#3890000
b0 +
b0 -
b0 3
b0 /
b11 9
b11 7
05
08
1*
1;
b0 ,
b0 .
b0 2
b0 4
1&
#3900000
0&
#3910000
b10 9
b10 7
1&
#3920000
0&
#3930000
b1 9
b1 7
0*
0;
18
b1 :
15
b0 6
1&
#3940000
0&
#3950000
b11 9
b11 7
05
08
1*
1;
b1 ,
b1 .
b1 2
b1 4
1&
#3960000
0&
#3970000
b1 +
b1 -
b1 3
b1 /
b10 9
b10 7
1&
#3980000
0&
#3990000
b1 9
b1 7
0*
0;
18
b10 :
15
b1 6
1&
#4000000
0&
#4010000
b10 +
b10 -
b10 3
b10 /
b11 9
b11 7
05
08
1*
1;
b10 ,
b10 .
b10 2
b10 4
1&
#4020000
0&
#4030000
b10 9
b10 7
1&
#4040000
0&
#4050000
b1 9
b1 7
0*
0;
18
b11 :
15
b10 6
1&
#4060000
0&
#4070000
b11 9
b11 7
05
08
1*
1;
b11 ,
b11 .
b11 2
b11 4
1&
#4080000
0&
#4090000
b11 +
b11 -
b11 3
b11 /
b10 9
b10 7
1&
#4100000
0&
#4110000
b1 9
b1 7
0*
0;
18
b100 :
15
b11 6
1&
#4120000
0&
#4130000
b100 +
b100 -
b100 3
b100 /
b11 9
b11 7
05
08
1*
1;
b100 ,
b100 .
b100 2
b100 4
1&
#4140000
0&
#4150000
b10 9
b10 7
1&
#4160000
0&
#4170000
b1 9
b1 7
0*
0;
18
b101 :
15
b100 6
1&
#4180000
0&
#4190000
b11 9
b11 7
05
08
1*
1;
b101 ,
b101 .
b101 2
b101 4
1&
#4200000
0&
#4210000
b101 +
b101 -
b101 3
b101 /
b10 9
b10 7
1&
#4220000
0&
