cpu_top/rtl/Execution_param.vh

// defines for adder
`define CTRL_ADD_WIDTH 2 
`define CTRL_ADD 2'b01
`define CTRL_SUB 2'b10
`define CTRL_ADDI 2'b11

//defines for shifter 


//defines for logic 
`define CTRL_LOGIC_WIDTH 3
`define CTRL_XOR 3'b001
`define CTRL_OR 3'b010
`define CTRL_AND 3'b011
`define CTRL_ANDI 3'b101
`define CTRL_XORI 3'b111
`define CTRL_ORI 3'b110
`define MSB_CTRL 2

//defines for branch control 
`define CTRL_BRANCH_WIDTH 3
`define CTRL_JAL     3'b000  // Jump and Link (JAL)
`define CTRL_JALR    3'b001  // Jump and Link Register (JALR)
`define CTRL_BEQ     3'b010  // Branch if Equal (BEQ)
`define CTRL_BNE     3'b011  // Branch if Not Equal (BNE)
`define CTRL_BLT     3'b100  // Branch if Less Than (BLT)
`define CTRL_BGE     3'b101  // Branch if Greater Than or Equal (BGE)
`define CTRL_BLTU    3'b110  // Branch if Less Than, Unsigned (BLTU)
`define CTRL_BGEU    3'b111  // Branch if Greater Than or Equal, Unsigned (BGEU)

cpu_top/sim/rvi32_instructions.vh
// rvi32_instructions.vh

// ChatGpt generated file with the given query 
// generate an header files in verilog defining all the RVI32 instruction and with their corresponding opcode . like define  ADD 0110011 
// RISC-V Instruction Categories and Bit Fields

`define R_TYPE 4'b000
`define I_TYPE 3'b001
`define LOAD_TYPE 3'b010
`define STORE_TYPE 3'b011
`define B_TYPE 3'b100
`define J_TYPE 3'b101
`define U_TYPE 3'b110
`define S_TYPE 3'b111



// R-type Instructions
`define R_TYPE_OP  7'b0110011
`define R_ADD       3'b000
`define R_SUB       3'b000
`define R_SLL       3'b001
`define R_SLT       3'b010
`define R_SLTU      3'b011
`define R_XOR       3'b100
`define R_SRL       3'b101
`define R_SRA       3'b101
`define R_OR        3'b110
`define R_AND       3'b111
`define R_FUNCT7_SRA 7'b0100000
`define R_FUNCT7_SRL 7'b0000000

// I-type Instructions
`define I_TYPE_OP  7'b0010011
`define I_ADD       3'b000
`define I_SLTI      3'b010
`define I_SLTIU     3'b011
`define I_XORI      3'b100
`define I_ORI       3'b110
`define I_ANDI      3'b111

// Load Instructions
`define LOAD_OP    7'b0000011
`define LOAD_LB    3'b000
`define LOAD_LH    3'b001
`define LOAD_LW    3'b010
`define LOAD_LBU   3'b100
`define LOAD_LHU   3'b101

// Store Instructions
`define STORE_OP   7'b0100011
`define STORE_SB   3'b000
`define STORE_SH   3'b001
`define STORE_SW   3'b010

// Branch Instructions
`define BRANCH_OP  7'b1100011
`define BRANCH_BEQ 3'b000
`define BRANCH_BNE 3'b001
`define BRANCH_BLT 3'b100
`define BRANCH_BGE 3'b101
`define BRANCH_BLTU 3'b110
`define BRANCH_BGEU 3'b111

// J-type Instructions
`define JAL_OP    7'b1101111
`define JALR_OP   7'b1100111

// U-type Instructions
`define U_TYPE_OP  7'b0110111
`define AUIPC_OP   7'b0010111

// SYSTEM Instructions
`define SYSTEM_OP  7'b1110011
`define ECALL      3'b000
`define EBREAK     3'b001

// Immediate Bit Fields
`define IMM_I   11:0
`define IMM_S   11:0
`define IMM_B   12:1
`define IMM_J   20:1
`define IMM_U   31:12

// Function Code Bit Fields
`define FUNCT3   2:0
`define FUNCT7   6:0

cpu_top/rtl/system_param.vh
//*******************
//this file  contains the crucial 
//system parameter like address width ,data width , 
//and other such parameters 


`define DATA_WIDTH 32 
`define INST_WIDTH 32 
`define REG_ADDR_WIDTH 5  
`define ADDR_WIDTH 32
`define OPCODE_WIDTH 7 
`define IMMEDIATE_WIDTH 21

cpu_top/rtl/Adder_int.v
//***************************************
//*Describes the basic adder unit structurally 
//and behaviorally 
//Date:6th august ,2024 : Risc Free Corp 
//****************************************
`timescale 1ns / 1ps
`include "system_param.vh"
`include "Execution_param.vh"
`include "rvi32_instructions.vh"

//
 module Adder_int(

	 //clk & reset 
	 input clk ,
         input reset ,
         input uop_valid_in,
	 //control 
	  input[1:0] add_type,
         // source 		  
	  input[`DATA_WIDTH-1:0] src1,
          input[`DATA_WIDTH-1:0] src2,
	  input[20:0] immediate ,
	  // output 
	  output[`DATA_WIDTH-1:0] add_value
	  // output equal ,
	  // output overflow ,
	  
	   
	  );


	  // These two registers hold the final operands for the add operation 
	  // based on the control logic , source operands are routed to these
	  // registers 

	  reg[`DATA_WIDTH-1:0] adder_src1 ,adder_src2;
	  reg[`DATA_WIDTH-1:0] src2_inp;
          reg[`DATA_WIDTH-1:0] add_value_reg;



	//  always@(posedge clk)   // Design issue #2 ,remove the clock 
	  always@(*)   // Design issue #2 ,remove the clock 
	  begin 
	     if(reset)
	     begin 
                 adder_src1={`DATA_WIDTH{1'b0}};
                 adder_src2={`DATA_WIDTH{1'b0}};
	     end 
             
          //   if(uop_valid_in) ,required for power savings , need to redesign later 
            // begin
	       case(add_type)

		       `CTRL_ADD :  begin src2_inp=src2; end 
		       `CTRL_SUB :  begin src2_inp= (~src2+1); end 
		       `CTRL_ADDI :  begin src2_inp={{(`DATA_WIDTH-21){1'b0}}, immediate};   end 
		       default :  begin src2_inp={`DATA_WIDTH{1'b0}}; end 
		      
              endcase 
         //   end 
              // store the operand1   
	       adder_src1=src1;

	       //store operand2 

               adder_src2=src2_inp;
	 // perform the final addition  
	// Design and optimize the adder topology and create a data path
	// optimizided code for this adder (*To do ) 

	       add_value_reg =(adder_src1 + adder_src2 );


	     
	    end  //always block  


        	 assign  add_value = add_value_reg;


  endmodule

cpu_top/tb/adder_tb.v
`timescale 1ns / 1ps

`include "Execution_param.vh"

module tb_Adder_int;

    // Parameters
    localparam DATA_WIDTH = 32;

    // Inputs
    reg clk;
    reg reset;
    reg [1:0] add_type;
    reg [DATA_WIDTH-1:0] src1;
    reg [DATA_WIDTH-1:0] src2;
    reg [20:0] immediate;

    // Outputs
    wire [DATA_WIDTH-1:0] add_value;

    // Instantiate the Unit Under Test (UUT)
    Adder_int uut (
        .clk(clk), 
        .reset(reset), 
        .add_type(add_type), 
        .src1(src1), 
        .src2(src2), 
        .immediate(immediate), 
        .add_value(add_value)
    );

    // Clock generation
    initial begin
        clk = 0;
        forever #10 clk = ~clk; // 20ns period
    end

    // Stimulus
    initial begin
        // Initialize Inputs
        reset = 1;
        add_type = 3'b000;
        src1 = 0;
        src2 = 0;
        immediate = 0;

        // Wait 100 ns for global reset to finish
        #100;
        
        // Deassert reset
        reset = 0;

        // Test ADD
        #20;
        src1 = 32'd15;
        src2 = 32'd10;
        add_type = `CTRL_ADD; // Assuming 3'b000 is `ADD` operation
        #20;
        $display("ADD: src1 = %d, src2 = %d, add_value = %d", src1, src2, add_value);

        // Test SUB
        #20;
        src1 = 32'd20;
        src2 = 32'd5;
        add_type = `CTRL_SUB; // Assuming 3'b001 is `SUB` operation
        #20;
        $display("SUB: src1 = %d, src2 = %d, add_value = %d", src1, src2, add_value);

        // Test ADDI
        #20;
        src1 = 32'd10;
        immediate = 21'd5;
        add_type = `CTRL_ADDI; // Assuming 3'b010 is `ADDI` operation
        #20;
        $display("ADDI: src1 = %d, immediate = %d, add_value = %d", src1, immediate, add_value);

        // Finish simulation
        #500;
        $finish;
    end

    // Dump variables for waveform viewing
    initial begin
        $dumpfile("tb_Adder_int.vcd");
        $dumpvars(0, tb_Adder_int);
    end

endmodule

cpu_top/sim/tb_Adder_int.vcd
$date
	Tue Aug  6 22:36:47 2024
$end
$version
	Icarus Verilog
$end
$timescale
	1ps
$end
$scope module tb_Adder_int $end
$var wire 32 ! add_value [31:0] $end
$var reg 2 " add_type [1:0] $end
$var reg 1 # clk $end
$var reg 21 $ immediate [20:0] $end
$var reg 1 % reset $end
$var reg 32 & src1 [31:0] $end
$var reg 32 ' src2 [31:0] $end
$scope module uut $end
$var wire 2 ( add_type [1:0] $end
$var wire 32 ) add_value [31:0] $end
$var wire 1 # clk $end
$var wire 21 * immediate [20:0] $end
$var wire 1 % reset $end
$var wire 32 + src1 [31:0] $end
$var wire 32 , src2 [31:0] $end
$var reg 32 - add_value_reg [31:0] $end
$var reg 32 . adder_src1 [31:0] $end
$var reg 32 / adder_src2 [31:0] $end
$var reg 32 0 src2_inp [31:0] $end
$upscope $end
$upscope $end
$enddefinitions $end
#0
$dumpvars
bx 0
bx /
bx .
bx -
b0 ,
b0 +
b0 *
bx )
b0 (
b0 '
b0 &
1%
b0 $
0#
b0 "
bx !
$end
#10000
b0 !
b0 )
b0 -
b0 0
b0 /
b0 .
1#
#20000
0#
#30000
1#
#40000
0#
#50000
1#
#60000
0#
#70000
1#
#80000
0#
#90000
1#
#100000
0#
0%
#110000
1#
#120000
0#
b1 "
b1 (
b1010 '
b1010 ,
b1111 &
b1111 +
#130000
b11001 !
b11001 )
b11001 -
b1010 /
b1111 .
b1010 0
1#
#140000
0#
#150000
1#
#160000
0#
b10 "
b10 (
b101 '
b101 ,
b10100 &
b10100 +
#170000
b1111 !
b1111 )
b1111 -
b11111111111111111111111111111011 /
b10100 .
b11111111111111111111111111111011 0
1#
#180000
0#
#190000
1#
#200000
0#
b11 "
b11 (
b101 $
b101 *
b1010 &
b1010 +
#210000
b101 /
b1010 .
b101 0
1#
